statmeasures/__init__.py
statmeasures/center.py
statmeasures/py.typed
statmeasures/spread.py
statmeasures/summary.py
statmeasures/utils.py
statmeasures-0.1.0rc3.dist-info/WHEEL
statmeasures-0.1.0rc3.dist-info/METADATA
statmeasures-0.1.0rc3.dist-info/RECORD
