Metadata-Version: 2.3
Name: statmeasures
Version: 0.1.0rc3
Summary: 
Author: oyghen
Author-email: oyghen <oyghen@duck.com>
Requires-Dist: scipy>=1.16.3
Requires-Python: >=3.11
